pybmds-25.1.dist-info/LICENSE.md
pybmds-25.1.dist-info/RECORD
pybmds-25.1.dist-info/WHEEL
pybmds-25.1.dist-info/entry_points.txt
pybmds-25.1.dist-info/top_level.txt
pybmds-25.1.dist-info/METADATA
pybmds/plotting.py
pybmds/batch.py
pybmds/constants.py
pybmds/bmdscore.pyi
pybmds/session.py
pybmds/__init__.py
pybmds/utils.py
pybmds/exceptions.py
pybmds/selected.py
pybmds/bmdscore.cpython-314-darwin.so
pybmds/reporting/styling.py
pybmds/reporting/__init__.py
pybmds/reporting/footnotes.py
pybmds/reporting/templates/base.docx
pybmds/types/nested_dichotomous.py
pybmds/types/multi_tumor.py
pybmds/types/ma.py
pybmds/types/dichotomous.py
pybmds/types/priors.csv
pybmds/types/session.py
pybmds/types/__init__.py
pybmds/types/common.py
pybmds/types/continuous.py
pybmds/types/priors.py
pybmds/datasets/nested_dichotomous.py
pybmds/datasets/dichotomous.py
pybmds/datasets/__init__.py
pybmds/datasets/continuous.py
pybmds/datasets/base.py
pybmds/datasets/transforms/__init__.py
pybmds/datasets/transforms/rao_scott.py
pybmds/datasets/transforms/polyk.py
pybmds/models/nested_dichotomous.py
pybmds/models/multi_tumor.py
pybmds/models/ma.py
pybmds/models/dichotomous.py
pybmds/models/__init__.py
pybmds/models/continuous.py
pybmds/models/base.py
pybmds/cli/priors_report.py
pybmds/cli/__init__.py
pybmds/.dylibs/libgsl.27.dylib
pybmds/.dylibs/libnlopt.0.11.1.dylib
pybmds/.dylibs/libgslcblas.0.dylib
pybmds/recommender/checks.py
pybmds/recommender/constants.py
pybmds/recommender/__init__.py
pybmds/recommender/default.json
pybmds/recommender/recommender.py
pybmds/stats/anova.py
pybmds/stats/__init__.py
