Metadata-Version: 2.1
Name: pybmds
Version: 25.1
Summary: U.S. EPA Dose Response Modeling Software
Author: BMDS Development Team
Author-email: Andy Shapiro <shapiro.andy@epa.gov>, Cody Simmons <simmons.cody@epa.gov>
License: MIT License
Project-URL: Source, https://github.com/USEPA/BMDS
Project-URL: Changes, https://github.com/USEPA/BMDS/blob/main/docs/source/history.md
Project-URL: Issue Tracker, https://github.com/USEPA/BMDS/issues
Project-URL: Documentation, https://usepa.github.io/BMDS/
Classifier: Intended Audience :: Science/Research
Classifier: License :: OSI Approved :: MIT License
Classifier: Programming Language :: Python :: 3.11
Classifier: Programming Language :: Python :: 3.12
Classifier: Programming Language :: Python :: 3.13
Classifier: Topic :: Scientific/Engineering
Requires-Python: >=3.11
License-File: LICENSE.md
Requires-Dist: matplotlib >=3.7
Requires-Dist: numpy
Requires-Dist: openpyxl
Requires-Dist: pandas >=2
Requires-Dist: pydantic >=2
Requires-Dist: python-docx
Requires-Dist: scipy
Requires-Dist: tabulate
Requires-Dist: tqdm
Provides-Extra: dev
Requires-Dist: poethepoet ~=0.32.2 ; extra == 'dev'
Requires-Dist: coverage ~=7.6.4 ; extra == 'dev'
Requires-Dist: mypy ~=1.13.0 ; extra == 'dev'
Requires-Dist: pybind11 ==2.13.6 ; extra == 'dev'
Requires-Dist: pytest-mpl ~=0.17.0 ; extra == 'dev'
Requires-Dist: pytest ~=8.3.3 ; extra == 'dev'
Requires-Dist: ruff ~=0.7.1 ; extra == 'dev'
Requires-Dist: setuptools ~=75.3.0 ; extra == 'dev'
Requires-Dist: wheel ~=0.44.0 ; extra == 'dev'
Requires-Dist: clang-format ==19.1.3 ; extra == 'dev'
Provides-Extra: docs
Requires-Dist: Sphinx ~=8.1.3 ; extra == 'docs'
Requires-Dist: myst-nb ~=1.1.2 ; extra == 'docs'
Requires-Dist: myst-parser ~=4.0.0 ; extra == 'docs'
Requires-Dist: furo ==2024.8.6 ; extra == 'docs'
Requires-Dist: sphinx-design ~=0.6.1 ; extra == 'docs'
Requires-Dist: sphinx-autobuild ~=2024.10.3 ; extra == 'docs'
